funapi/__init__.py
funwork-0.0.1.dist-info/LICENSE
funwork-0.0.1.dist-info/METADATA
funwork-0.0.1.dist-info/WHEEL
funwork-0.0.1.dist-info/entry_points.txt
funwork-0.0.1.dist-info/top_level.txt
funwork-0.0.1.dist-info/RECORD
