Metadata-Version: 2.1
Name: funwork
Version: 0.0.1
Summary: funwork
Home-page: https://github.com/farfarfun/funwork
Author: bingtao
Author-email: 1007530194@qq.com
License-File: LICENSE
Requires-Dist: funpypi
Requires-Dist: funfile
Requires-Dist: requests
Requires-Dist: tqdm
